SharekhanApi/__init__.py
SharekhanApi/sharekhanConnect.py
SharekhanApi/sharekhanExceptions.py
SharekhanApi/sharekhanWebsocket.py
test/__init__.py
test/test.py
shareconnect-1.0.0.11.dist-info/METADATA
shareconnect-1.0.0.11.dist-info/WHEEL
shareconnect-1.0.0.11.dist-info/top_level.txt
shareconnect-1.0.0.11.dist-info/RECORD
