Metadata-Version: 2.1
Name: shareconnect
Version: 1.0.0.11
Summary: Sharekhan Data Feed Trading Api Server
Home-page: UNKNOWN
Author: rg-sharekhanapi
Author-email: shareconnect@sharekhan.com
License: UNKNOWN
Platform: UNKNOWN
Classifier: Intended Audience :: Developers
Classifier: Programming Language :: Python
Classifier: Natural Language :: English
Classifier: Programming Language :: Python :: 2.7
Classifier: Programming Language :: Python :: 3.5
Classifier: Programming Language :: Python :: 3.6
Classifier: Programming Language :: Python :: 3.7
Classifier: Topic :: Office/Business :: Financial :: Investment
Classifier: Topic :: Software Development :: Libraries :: Python Modules
Classifier: Topic :: Software Development :: Libraries
